{
  "creds": {
    "noiseKey": {
      "private": {
        "type": "Buffer",
        "data": "OGmgY0FYL9n9CdzEcT9iTqJCdcrdRdzyG04N5AmFcXs="
      },
      "public": {
        "type": "Buffer",
        "data": "2wZSEYGMDgbpIbcgy4/jr+A/5EIicur2JaeHnzO4BkE="
      }
    },
    "signedIdentityKey": {
      "private": {
        "type": "Buffer",
        "data": "QHdQTBJ02r6hGW+J2mlT9QQpf83T46u2ioT8gc7xv1s="
      },
      "public": {
        "type": "Buffer",
        "data": "iLXjfkqXy7Z/OqNIJf7KE0Xzxeif3Qjj2ddpYC3gfEI="
      }
    },
    "signedPreKey": {
      "keyPair": {
        "private": {
          "type": "Buffer",
          "data": "0D6TAZ+C1LjPhGP5YB3wvsEeNax5n4Ojib/L+M+PkEs="
        },
        "public": {
          "type": "Buffer",
          "data": "P+0iAqgYs2j1OYp2xHPSvS0mBqJeRQf7lzcRiKrGvjI="
        }
      },
      "signature": {
        "type": "Buffer",
        "data": "stKP3yYPjYmVZSwowmIUZ5+4DpQvX9O/POzaAYwWCd/blZScBPKMQjJ5dLpmB9wfSzILNgoe26gJk5cCbKjpjg=="
      },
      "keyId": 1
    },
    "registrationId": 28,
    "advSecretKey": "4a8tkywWU1R+JkjQo2qjlobeV8qZIPEFtjO90FEOxtQ=",
    "processedHistoryMessages": [
      {
        "key": {
          "remoteJid": "6281236167286@s.whatsapp.net",
          "fromMe": true,
          "id": "F32BDAA95F89EF7D28AD1D9B0FFFF1C0"
        },
        "messageTimestamp": 1664510876
      },
      {
        "key": {
          "remoteJid": "6281236167286@s.whatsapp.net",
          "fromMe": true,
          "id": "B7C6949EF49E00C7C1D7445BCAC9B669"
        },
        "messageTimestamp": 1664510876
      },
      {
        "key": {
          "remoteJid": "6281236167286@s.whatsapp.net",
          "fromMe": true,
          "id": "A7CAB209BC320541B6FBC7B846DB9E05"
        },
        "messageTimestamp": 1664510895
      }
    ],
    "nextPreKeyId": 31,
    "firstUnuploadedPreKeyId": 31,
    "accountSettings": {
      "unarchiveChats": false
    },
    "account": {
      "details": "CO2yyMUBEJDX2ZkGGAE=",
      "accountSignatureKey": "NUbmISmjhVLBr7aYAdpJ+72PKysdQe5hgb244ys4FRM=",
      "accountSignature": "S0VSCFtW7beBxYDedQJ7FXY9JIULNZWYi1kOXXQkVzahtjrmKAcftcz/lvNIj7LWa9rwiJ6wHW2lz24T56H6BQ==",
      "deviceSignature": "Nx5DOOuozkl5NS9xWGofZduwXo8jMFGOTIK65XZH97zYxwWvW+ln3U5wpcW+kvdRKIKnDWV+nqAGnapaZO+chg=="
    },
    "me": {
      "id": "6281236167286:4@s.whatsapp.net",
      "name": "S#_:6"
    },
    "signalIdentities": [
      {
        "identifier": {
          "name": "6281236167286:4@s.whatsapp.net",
          "deviceId": 0
        },
        "identifierKey": {
          "type": "Buffer",
          "data": "BTVG5iEpo4VSwa+2mAHaSfu9jysrHUHuYYG9uOMrOBUT"
        }
      }
    ],
    "platform": "android",
    "lastAccountSyncTimestamp": 1664510873,
    "myAppStateKeyId": "AAAAAEIC"
  },
  "keys": {
    "preKeys": {
      "1": {
        "private": {
          "type": "Buffer",
          "data": "cHnQyuoVJ9bkOeD3ltlz8oAsgPAclbsaB6dfbhyF01Y="
        },
        "public": {
          "type": "Buffer",
          "data": "YJzBMb0vO104bQZXpRfM9qApkB5u6LGD0qIec7A5xRg="
        }
      },
      "2": {
        "private": {
          "type": "Buffer",
          "data": "2J51HGCr5uyh3KuTzIOkGcJ3DmMzDM4yEvkO9Pm6bk0="
        },
        "public": {
          "type": "Buffer",
          "data": "WuLOMkbMZnYOMUYwQlQNCdQaAbkbablgdJFgIzbDSnQ="
        }
      },
      "3": {
        "private": {
          "type": "Buffer",
          "data": "YGLWzSuCZVMj9IDi/y3JId/+xA4uPwIq6iUL/P6SRmU="
        },
        "public": {
          "type": "Buffer",
          "data": "UuFIBATY6belhRvQMaO0Fa2+5jsOAcqFvtbr54jkKAA="
        }
      },
      "4": {
        "private": {
          "type": "Buffer",
          "data": "IKpWdeMaP/LNGDB+YUEtRiLJGU5zfBwZNDNfEdionFY="
        },
        "public": {
          "type": "Buffer",
          "data": "kdX5fLHKwLvliC8demAfP0gnhB3sbL9sDKXH/EDxGBM="
        }
      },
      "5": {
        "private": {
          "type": "Buffer",
          "data": "QFSDSElwLNaIcqCYUlTsq1WWWrhGpO9XVFyMJo2nAkU="
        },
        "public": {
          "type": "Buffer",
          "data": "InFZ4ISA2VSO/eRi+SYS9G/ESWPktJGtV+kSWKd3ukk="
        }
      },
      "6": {
        "private": {
          "type": "Buffer",
          "data": "wLxNAhL6QZguyKIeoQUDSJNdAe5ooS7kOpyYwMdf3kE="
        },
        "public": {
          "type": "Buffer",
          "data": "1aSpMzMEOZz0nHP4YFggrIUw03wDthUlViy9G/k2bDo="
        }
      },
      "7": {
        "private": {
          "type": "Buffer",
          "data": "WMhGUQi96QMgZ3UsYfVqo1WY0EVVUwN0P2WdYnOhlU8="
        },
        "public": {
          "type": "Buffer",
          "data": "yM+IMwfwavz0cAJi8QDpTZTy1qGIlRmU7J6mwD2rGSY="
        }
      },
      "8": {
        "private": {
          "type": "Buffer",
          "data": "AKhq6gNdE4zNyixM8jE2U9SmUPigs7c52ITYGbTeEF4="
        },
        "public": {
          "type": "Buffer",
          "data": "oRiVzFnJXbCM+04XjzwX4M3pFbwSmWV5VOv7CUhG/3A="
        }
      },
      "9": {
        "private": {
          "type": "Buffer",
          "data": "IHp1ehN5l9bRhTmG1HrFApChGg5o5PoI8D+kh6lGlW4="
        },
        "public": {
          "type": "Buffer",
          "data": "mcfy4KsuxqLWaiLQAC7hwvBn3724b1e7gu5AD9knq0s="
        }
      },
      "10": {
        "private": {
          "type": "Buffer",
          "data": "yLLYxZP9RhHiu+jucBzLEn36FwaWN9GTECIkh9jAnnc="
        },
        "public": {
          "type": "Buffer",
          "data": "DxxiNJjJAF8vIhVh7ULv5rQgOcph591nR93SDWn+mj0="
        }
      },
      "11": {
        "private": {
          "type": "Buffer",
          "data": "CO+rcJXHsWM3l/6/pLtAo+UaPFa9grE4aukCK0RYNHs="
        },
        "public": {
          "type": "Buffer",
          "data": "M2Ua8OeSLfWBX6/F2N/cGngQmywqdZqhDQ7HmP8rm38="
        }
      },
      "12": {
        "private": {
          "type": "Buffer",
          "data": "YPA8IbH0hTEEnLXf/TqHWDDjB+4g+zrGYZWLjR8vvlM="
        },
        "public": {
          "type": "Buffer",
          "data": "LyjwOY+HAqHoZe5oBWnuNBmB37e9oppCTudT0RDpjXk="
        }
      },
      "13": {
        "private": {
          "type": "Buffer",
          "data": "YFyCUWP0Is3cdFakZSlr7n1X+bTRrHGU0q9BSHFRaW4="
        },
        "public": {
          "type": "Buffer",
          "data": "X4sU1xRXFg4ZP+E8KNoKH17AvPHbk0QIcJN0cZUv81M="
        }
      },
      "14": null,
      "15": null,
      "16": {
        "private": {
          "type": "Buffer",
          "data": "QCTKJggCHcsp2okmGCm1Mi0jJOyknHeZ/yVGiUnIcXg="
        },
        "public": {
          "type": "Buffer",
          "data": "wgofH31thkch2AF472riLd9HbfNQf5qckRFF3NJSSmM="
        }
      },
      "17": {
        "private": {
          "type": "Buffer",
          "data": "uBlj3/Pjwhu0v7lwwJOVOt0qBZk6HiYNmb0lK/UQNUg="
        },
        "public": {
          "type": "Buffer",
          "data": "JOGDgvKMdnfJ1w3gMADLW37BZ2mqTGl5oi3v7iYY4Co="
        }
      },
      "18": {
        "private": {
          "type": "Buffer",
          "data": "QB9vQxDL2K444cY9oLyx8qYGmMQV2q6hnawKedSCCnM="
        },
        "public": {
          "type": "Buffer",
          "data": "qZeot9wEVUKfET3FnOjpinnimwHTi0llNEzekNqNI1Q="
        }
      },
      "19": {
        "private": {
          "type": "Buffer",
          "data": "wCF5/RCKwHQUUVYtq0Q/pb1YUElejeXbHAmLxj02FWE="
        },
        "public": {
          "type": "Buffer",
          "data": "7Tar3oq16SE/dF4aENNnlrdwZs7uStqDHRxC30ubvms="
        }
      },
      "20": {
        "private": {
          "type": "Buffer",
          "data": "aAJGDQUr36K0dYeTdsrH1txSsjL2ZE1VOz1NPDNf/3Q="
        },
        "public": {
          "type": "Buffer",
          "data": "o31UskPTYcZ3fAhbvNeJtA8RNAlwKfiz06FaqsGIqUE="
        }
      },
      "21": {
        "private": {
          "type": "Buffer",
          "data": "+JDi89+6Kz3RbKbpu8YqQwJeLCZB9VgRgHkc7LTe/m8="
        },
        "public": {
          "type": "Buffer",
          "data": "W7kqFEB4y8qi/vd9sK7ofolQrLODccd2EBU18qGik04="
        }
      },
      "22": {
        "private": {
          "type": "Buffer",
          "data": "iM7s7qQyKG9HS14+s5UXEbcuZbn3ABZShgkaGvitjGs="
        },
        "public": {
          "type": "Buffer",
          "data": "NtlW0lDFCxftoXwZZeAK+FGgo9X+rJ+f1IfF/pz7sGc="
        }
      },
      "23": {
        "private": {
          "type": "Buffer",
          "data": "wL5ulDvyVXJHH3HJU52QCBfQ8/zZI2eYxiU0ROHWmWg="
        },
        "public": {
          "type": "Buffer",
          "data": "OcwqMA5/1ZdKEaLvnoSNyT4yB4NUQLejKyY8XQoDkVE="
        }
      },
      "24": {
        "private": {
          "type": "Buffer",
          "data": "KLsKoUyUsozyLGO73e3rD5+unA8WRCQt87sOiVKEZV4="
        },
        "public": {
          "type": "Buffer",
          "data": "HM5//zG5hposNnrF79iwHFOPnmoExRMw0xKzRNdlUXU="
        }
      },
      "25": {
        "private": {
          "type": "Buffer",
          "data": "sLsFS5LdAGAAeXwQMZ5PzSb4MtSzvZ7JxtRwKyDCimQ="
        },
        "public": {
          "type": "Buffer",
          "data": "px2nN4K2GHg4AlLmHynggLnMI4TV6NEJM0mW2Ad4q1w="
        }
      },
      "26": {
        "private": {
          "type": "Buffer",
          "data": "gJ4gaCflxNY5ekYZUeyr54ZeYWzc7xAoJAKpQtwBkVc="
        },
        "public": {
          "type": "Buffer",
          "data": "tPGun7ecraIm4VZxk5Px99vrd+qEIc1M7obSMaVCdFc="
        }
      },
      "27": {
        "private": {
          "type": "Buffer",
          "data": "8KL6c/RHtlRhGNFtEpkuENYklf8Bqn5RPeWTm01DhEw="
        },
        "public": {
          "type": "Buffer",
          "data": "HvYRgnflFH5NO4L2fOK3z7jbLT+Ao/GfylJMHVAdmD4="
        }
      },
      "28": null,
      "29": {
        "private": {
          "type": "Buffer",
          "data": "6J/syulr/jQ8cTokXPjYjaN+zIfpH+IHfOa9cK5Ne3A="
        },
        "public": {
          "type": "Buffer",
          "data": "IHMvExnoWk0T6hsnP5zGlEV4nKU8E8Qq8WeFi0gAAh4="
        }
      },
      "30": {
        "private": {
          "type": "Buffer",
          "data": "2M8pqWQnx0L8Yh6nMBe0gNExBM4e+Fs3yVRhN8mCzVs="
        },
        "public": {
          "type": "Buffer",
          "data": "PXmIKqJahYlo+C1zZ2x9Os4hReZ26VONU9CeJUZV5jo="
        }
      }
    },
    "sessions": {
      "6281236167286.0": {
        "_sessions": {
          "BVwnEsT9YnTkcpAcEQLEauj+mkQUBMaQqpeJ1qgXEohy": {
            "registrationId": 407419711,
            "currentRatchet": {
              "ephemeralKeyPair": {
                "pubKey": "BQqM9vkWabUGSleT6pHKoPlm2oPbI78PbIiV07575XAY",
                "privKey": "AFSHtfSUqnfLh+iRAngxkdLukcB6wOwb65kzEShPlkI="
              },
              "lastRemoteEphemeralKey": "BdPHSulz5zZ/hf+X3v9LJjDUHW+O7C0xRCzIjJz3ZSl5",
              "previousCounter": 0,
              "rootKey": "zvMe0HDip8CBEpfbru5K75GuWkE6VUztmKEzWVMNIiQ="
            },
            "indexInfo": {
              "baseKey": "BVwnEsT9YnTkcpAcEQLEauj+mkQUBMaQqpeJ1qgXEohy",
              "baseKeyType": 2,
              "closed": -1,
              "used": 1664510876236,
              "created": 1664510876236,
              "remoteIdentityKey": "BTVG5iEpo4VSwa+2mAHaSfu9jysrHUHuYYG9uOMrOBUT"
            },
            "_chains": {
              "BdPHSulz5zZ/hf+X3v9LJjDUHW+O7C0xRCzIjJz3ZSl5": {
                "chainKey": {
                  "counter": 8,
                  "key": "Xk4nzTFMA+x3jQmcXL9W6Z81LhN8sCxrpxRbocWWoB4="
                },
                "chainType": 2,
                "messageKeys": {}
              },
              "BQqM9vkWabUGSleT6pHKoPlm2oPbI78PbIiV07575XAY": {
                "chainKey": {
                  "counter": 0,
                  "key": "CxD/HxfbecZCyG1pAWGQUWmSNTFE6oan4xDyuu2Ji1k="
                },
                "chainType": 1,
                "messageKeys": {}
              }
            }
          }
        },
        "version": "v1"
      },
      "6281572757041.0": {
        "_sessions": {
          "BbOFByyhcgnWoHycbqHVTJ+I65Yi5CgstMm7rT3ULK4R": {
            "registrationId": 1224990547,
            "currentRatchet": {
              "ephemeralKeyPair": {
                "pubKey": "BesJzyQSPDNf9pXdafVw3CCDlWkiPAlbRCtK6Y2XYTQt",
                "privKey": "2ImZxFhkwhVVSwWYwr914xETxBwSTRPDxvdWEHiAA3E="
              },
              "lastRemoteEphemeralKey": "BQaM88F29B+VhfFfX3S22pIsI4kRMUpQMvRPGFEqez8S",
              "previousCounter": 0,
              "rootKey": "srLYYmsMdCmoiohbGcYrjiAfvtvjm+HUviFV9yDIAYI="
            },
            "indexInfo": {
              "baseKey": "BbOFByyhcgnWoHycbqHVTJ+I65Yi5CgstMm7rT3ULK4R",
              "baseKeyType": 2,
              "closed": -1,
              "used": 1664510913631,
              "created": 1664510913630,
              "remoteIdentityKey": "BaG/oyjqVPQDVCYpXU+sEIlQpHXfbhDa48exbuo3S1hA"
            },
            "_chains": {
              "BQaM88F29B+VhfFfX3S22pIsI4kRMUpQMvRPGFEqez8S": {
                "chainKey": {
                  "counter": 0,
                  "key": "pMg6R9GlUg2qcGuy7AuWheRLiPDLotD3im7vUq02Tao="
                },
                "chainType": 2,
                "messageKeys": {}
              },
              "BesJzyQSPDNf9pXdafVw3CCDlWkiPAlbRCtK6Y2XYTQt": {
                "chainKey": {
                  "counter": 0,
                  "key": "ojcEo1yX767yOcX+ho0nnIvyuWEuXpyRPFNpCqAnlDQ="
                },
                "chainType": 1,
                "messageKeys": {}
              }
            }
          }
        },
        "version": "v1"
      },
      "6287832895242.0": {
        "_sessions": {
          "BR3fSqncO2Oj/MD9G2YnvuNpDoMU6M/5kv3wIYDeKQkD": {
            "registrationId": 1030739590,
            "currentRatchet": {
              "ephemeralKeyPair": {
                "pubKey": "BRdhCDMNwVXfxsy9T6962LYTNQfdWvmOZKMSW5/Q765Q",
                "privKey": "2F69k7o51r66mm8lp4wEzIKD/rG7wc2+Mqp4Ya6aeEY="
              },
              "lastRemoteEphemeralKey": "BV91e0c2wh/sRtdz0k8h8nT2TV/Uir3Zo8DQQ6GRXFUh",
              "previousCounter": 0,
              "rootKey": "TKUA2FUYTeUWQPli2Jrn5G1DOewEs4v0PXL34g4i3uM="
            },
            "indexInfo": {
              "baseKey": "BR3fSqncO2Oj/MD9G2YnvuNpDoMU6M/5kv3wIYDeKQkD",
              "baseKeyType": 2,
              "closed": -1,
              "used": 1664510947571,
              "created": 1664510947571,
              "remoteIdentityKey": "BYN2SAgl51J4dbkrIG4azNkCQeDaY1PzqLTahKrfeaAl"
            },
            "_chains": {
              "BV91e0c2wh/sRtdz0k8h8nT2TV/Uir3Zo8DQQ6GRXFUh": {
                "chainKey": {
                  "counter": 0,
                  "key": "zZL+WYzdEsPPqKISfqN52RzEY3HYiAsgHSx4GxXRM3Y="
                },
                "chainType": 2,
                "messageKeys": {}
              },
              "BRdhCDMNwVXfxsy9T6962LYTNQfdWvmOZKMSW5/Q765Q": {
                "chainKey": {
                  "counter": -1,
                  "key": "K1W8L0Vy8DOFeLnbkPZ1U2k099kLvAFtJu5SS6Dk8Yc="
                },
                "chainType": 1,
                "messageKeys": {}
              }
            }
          }
        },
        "version": "v1"
      }
    },
    "senderKeys": {
      "120363045542910570@g.us::6281236167286::0": [
        {
          "senderKeyId": 1184003416,
          "senderChainKey": {
            "iteration": 4,
            "seed": "Jpftqz3lFDoBC8WuTjExokrfGjTmjUqR6454q4YlI7I="
          },
          "senderSigningKey": {
            "public": "BXl9UEGBtdN9R5U1+nOzV4LfsGarx1S/fmqt2N35BeQk"
          }
        }
      ],
      "120363045542910570@g.us::6281572757041::0": [
        {
          "senderKeyId": 1192387960,
          "senderChainKey": {
            "iteration": 3,
            "seed": "ZllFNvcFl8oFrdRxYVI/1hNUAf3I8YTe4K6Jwg9bXq0="
          },
          "senderSigningKey": {
            "public": "BWKJ1BtZ76JWAb84u43ofzuJWiC0TDAGoCvpvQ6Ocrl5"
          }
        }
      ],
      "120363045542910570@g.us::6281236167286:4::0": [
        {
          "senderKeyId": 1536334969,
          "senderChainKey": {
            "iteration": 2,
            "seed": "ZOijmWaNkKNs3CWWpaBpNgKIBkDR/xAhFT6W9HYGgsg="
          },
          "senderSigningKey": {
            "public": "BUEIbpjY7C14CP7Ju0Brf40IwlaMYvOemOvV3DSk+iw+",
            "private": "OBi/1DSLw8+/R95EWygZHnhGXzTgrK+JtSimzPk21k8="
          }
        }
      ],
      "120363025216389564@g.us::6287832895242::0": [
        {
          "senderKeyId": 609123616,
          "senderChainKey": {
            "iteration": 1,
            "seed": "t1kJaw+ip4e4y2qq5AkcckBcoRTa5Ns8ESSaLyf31s0="
          },
          "senderSigningKey": {
            "public": "BXJHk32eNqie4XIL23QOS3AKnDQozmgkgyGiibPPbecX"
          }
        }
      ]
    },
    "appStateSyncKeys": {
      "AAAAAEIC": {
        "keyData": "QOY3fFKl744DHLmxhNXBVVmjMS3GIQ9pTJJOaOTL794=",
        "fingerprint": {
          "rawId": 414325101,
          "currentIndex": 1,
          "deviceIndexes": [
            0,
            1
          ]
        },
        "timestamp": "1664510874101"
      }
    },
    "appStateVersions": {
      "critical_block": {
        "version": 1,
        "hash": {
          "type": "Buffer",
          "data": "1IC73g4pDwNhp64YivPx3quYj4zZunft9vgZggbnp75Fd3xDePzq5aOr+wbOw45O+fL+Qm0OYxzhzF+5qzIKudi7YRYae7hjbwUuZ3enGLBBzAvl/BIHHwGO7kJ6OCExvTElGcg+Qk/LBgrONUzz8YTffkBWQBuhfIDcWZ32N5c="
        },
        "indexValueMap": {
          "fwjQpiiAyjSTpIJVi2McClcGRoWSNioy8iz96J8AYNQ=": {
            "valueMac": {
              "type": "Buffer",
              "data": "OItuxLg4r1DMf93tawah9DoPxzWnsASmxIp9qphM01I="
            }
          },
          "RRv15rWvDQptnLeIKeORuuDRs5xjlU58F7kl0goErVg=": {
            "valueMac": {
              "type": "Buffer",
              "data": "0mU0xZpmr9HFyjwNyWopkLj1oLls+ru5q+4iMpTJlOA="
            }
          }
        }
      },
      "regular": {
        "version": 1,
        "hash": {
          "type": "Buffer",
          "data": "hTlFuSC9qJGFNvu3OhtYurfXHcfxhW0KpsaqB/Zzv0LdT2RUBFsiP/feegQfEMKwL/AHbarJphLNVBGlSG6ZX/oyDrN0rkXpm0o/djDQTEtC1xRTQSESOF/pKMiJ/zCqZewtVRrNZpkbptGbwj9nlIgXbe0LULyNNJwbvIM+dPQ="
        },
        "indexValueMap": {
          "nP/GkvbWqIX/ZMDCVEymB1LOoGlulN7cWxCP2i7nPsA=": {
            "valueMac": {
              "type": "Buffer",
              "data": "OB1teWaqtXJKlaUtCZnVLaHAhqhZtK1FoHfmphQSgZs="
            }
          }
        }
      },
      "critical_unblock_low": {
        "version": 1,
        "hash": {
          "type": "Buffer",
          "data": "rYu6PtFXt1dJZPvAlF8JlIAMsv9MAKDlFgOtKrRS7K9U7SMqMfUKzrd6+Z0rSjegpPfmomJWHnKhLt8+0iBdQkgJcXcmQfOx9nkacqsLIFElLgYZgCGmRXjo2BVpoo/gRes7jzz5N0JjJdjiDmgkjwt/tLJ34599q10jmPI/DiA="
        },
        "indexValueMap": {
          "kkV7cn1TqajtvUjg4rwwxOZLYIsRmdJgO7ELIIYKcfk=": {
            "valueMac": {
              "type": "Buffer",
              "data": "AWHie7Inby22ce31ObkhOMn5S0S7ycp7K44E8aRrx4s="
            }
          },
          "gTudx19ibwCYYcV7fsRvU4ZVOj7D8qy5do/sXP4MNek=": {
            "valueMac": {
              "type": "Buffer",
              "data": "LEKSl52okfZBbje3raeAUTUcXOlrV/2XPgQBPltiuUY="
            }
          },
          "/1M7+qoghsyxPMLvltyoYxkBucVKzWqNkZXrdJ+SCb0=": {
            "valueMac": {
              "type": "Buffer",
              "data": "6xpe42YmWCNRN3GgxORXLtqUoWC0y75JgnptpdPEBbA="
            }
          },
          "OQ9i1ziAaHR1aBVLyWETIHtpsJwdXpoxJWUXMGTD4Ds=": {
            "valueMac": {
              "type": "Buffer",
              "data": "9YOHQnd1TDroTuzFiYI1EbVC0rXu5jZTE292lKk3dVk="
            }
          },
          "Vkfv6EjrEHcITFMeO9rHOA6d2hVdCPYNnQh8DGf3sI4=": {
            "valueMac": {
              "type": "Buffer",
              "data": "+LTUzXFhnRH+6GBQ486F55KG/Yp3R8ZeAXFTgQu/jrA="
            }
          },
          "5aZnTnJl60BoHPnnTFGDUuGNDf/4m9T9PnpuK4o8nNs=": {
            "valueMac": {
              "type": "Buffer",
              "data": "D9j0q1xou/NgxzhCSOSIHg/TUtqvFiWVwThCLwOUEpk="
            }
          },
          "7JBpgjzsNY31KRl/IRPzlfphHfYBGve/QrPSoMbdCKQ=": {
            "valueMac": {
              "type": "Buffer",
              "data": "dgaXNx+uRJWaeJa/HU9SIyjLHVI+NZS/ThkU0svaldU="
            }
          },
          "4hyjAkNM6Btgb1Hfl+t447oaCSD5PcacbgvM9JDtv+A=": {
            "valueMac": {
              "type": "Buffer",
              "data": "euAWvFZDP95/GcgtbgRSvjNjouoOl+qiUo321K+pWOk="
            }
          },
          "zntnSLBpMngPMHGpivgUiWa2+XhtDetBQyDMBoKJVr8=": {
            "valueMac": {
              "type": "Buffer",
              "data": "u/KPsuyald4QLLB1F3ASNOQ5cv05uPYkvAaFHaBSqjc="
            }
          },
          "lGClzTvSYTi0AnzROy27a2ttviKoTyPSTiL0e2qPJLo=": {
            "valueMac": {
              "type": "Buffer",
              "data": "bH1nkwPnXEOVPEKWg3KM9Bem+vwdI5tvF45e0dDqNaw="
            }
          },
          "2OuHTVBUA+Ia4qIrtFDSiYBZwr5NAGbWM+zCuXpzYEA=": {
            "valueMac": {
              "type": "Buffer",
              "data": "LEv8ONdBSc0zfQf07fwEBIuYPJySdLowx1Sv88l3FMY="
            }
          },
          "VVDU0D/0HV18D0asND8/hdLED+sT1dLJj6oeT9d5XzM=": {
            "valueMac": {
              "type": "Buffer",
              "data": "Z/Uf0d9mkAO4ze4OdOb+jlqCZRvhuyqyBZFdR9gGqRc="
            }
          },
          "i4sO3FzxOqDCcMKevhBOxg4EA9eJlHxEMcZ6jEAlUeA=": {
            "valueMac": {
              "type": "Buffer",
              "data": "OjYP+nW5NLUVm99/vL12hZR+sJJREoH6goHtI4CDQIs="
            }
          },
          "DmtAlcu/YMxqjns87J0uxvfbHSvuIdD3iH71M0PHbgI=": {
            "valueMac": {
              "type": "Buffer",
              "data": "xCLR+Gvz9XXWHOzS6wWjo9KlrRUKBmFwD9c9NlTY9BY="
            }
          },
          "7piwLONno+QiiSOThSRb/unVoKm8AV0C6OxY85aydhQ=": {
            "valueMac": {
              "type": "Buffer",
              "data": "acp3Ixp+8N/tkFiVaodpJzVEEPuRAXJDn7bP5BleBAg="
            }
          },
          "TztvMegvVj4S3u5yxSwoC1JFxk5z5Z+sNCyf1maaDyw=": {
            "valueMac": {
              "type": "Buffer",
              "data": "RDeZ6mQ5+/no0OTHpdZHKYEzJSVxQ9sGqeVW8y7Gi5c="
            }
          },
          "a6ett29LOZCoz4+DJ5cqiFBn2qjXZAe/G/xioQmTT5E=": {
            "valueMac": {
              "type": "Buffer",
              "data": "4j3VNG9kUy97u0QOpUCnAGlONl3N7WnXRJG5rQN2YZo="
            }
          },
          "zsgJffl94iUJKfKuReCTZGZa0AHyoz1xnEYWxThsT6w=": {
            "valueMac": {
              "type": "Buffer",
              "data": "KzWPtCmTh8aXje6NN8TT+5/sHHO5ATQC/VOUdCke49w="
            }
          },
          "twBxINCpMgtK1PXi8Ci2r1DJPnqnpXgdr7nlHVQsJ08=": {
            "valueMac": {
              "type": "Buffer",
              "data": "wbfc16UR4dPCGmbrBeh2VuDJiTdjyxj2eDyxSaGUz9s="
            }
          },
          "jtTIzuwZGxsZZ/dPAxCTy+oUsqzpVBapqE8/Pnsl/qo=": {
            "valueMac": {
              "type": "Buffer",
              "data": "wjYPdTE3ko0KqPJSpUHBhgGnqe3WpqMW3jw54k5LWgw="
            }
          },
          "KCLaf1V6qkjy7nixm5ZOiG6aG9znuOuU9XmenXy8mI4=": {
            "valueMac": {
              "type": "Buffer",
              "data": "2/FC+azXWKJCBoas77WYIph3fmi/gVP3xAXAzdWuYpc="
            }
          },
          "unQXfw5c6lNhHg+W9LYolDDkTpXC/yc8tlJ9PvZm0Sk=": {
            "valueMac": {
              "type": "Buffer",
              "data": "we7qxhAFO6q+4HDPe3nrPsBRaFTMmaiUCqCv/yjuBeo="
            }
          },
          "XVsW27mIf48sBMWc43OfBLcerVOjLr0T61jj64MUvmk=": {
            "valueMac": {
              "type": "Buffer",
              "data": "l74hyKVCZxGYd+/czXjHA6RbxmAZE/+FUdD0lE9lIKo="
            }
          },
          "CWx8oZvzuSmMGB1Tza4GxvfawKXaE6PRQromz+mmTzU=": {
            "valueMac": {
              "type": "Buffer",
              "data": "iUWQLdldhjAIxbX+LPzwzbed/jr+QHGXzVziDEkpMzk="
            }
          },
          "P0ABIvBoI+nxn8pke/1vspPwWUkMS8DhxLcM9tM0PqQ=": {
            "valueMac": {
              "type": "Buffer",
              "data": "tZLXvR3bQc2cKlIVGe8pB4C0JdYkBOeTxAEEGVI4TXg="
            }
          },
          "d9isr+3XJ4DHuOFp65mpACyLJPBln26cpAPG2NYhSUE=": {
            "valueMac": {
              "type": "Buffer",
              "data": "mxLaIrcRNt0fcGRdsjqN8PbGs1tEBtEQE1DfwDGDFOw="
            }
          },
          "Oi2a0Vekt9uxtDbuSrLIZz6PyQOCp+IuKpptqMHFhJU=": {
            "valueMac": {
              "type": "Buffer",
              "data": "yoDZ84SucgBX/9erDFX+QLZEhv+cYpI/dl93Uu0cmH4="
            }
          },
          "/qCeX8VUj2nTmkY8BcgweZzY9lTidOM/GGHNvHsmJtc=": {
            "valueMac": {
              "type": "Buffer",
              "data": "zpt9AckxVkTOeC53SZt85EP2x2BcJYSKK6QjdDgzkn8="
            }
          },
          "NS0RdmlVdfE4cVQt/+KTM0VvDL4DCZnzk0l8CZRYcJc=": {
            "valueMac": {
              "type": "Buffer",
              "data": "6A1A8YXAETv4TBy5LQwFi5iTW5Nr9AHdC3yI3jh0YVQ="
            }
          },
          "p5kt1yX8kHzPRmpPqlPED7CZYS/26fpSCT+BfzyAFKg=": {
            "valueMac": {
              "type": "Buffer",
              "data": "P0YhZpCLZhb40SfBA8jsk2mvDHYVIzF2J0VbSRA3vzA="
            }
          }
        }
      },
      "regular_high": {
        "version": 1,
        "hash": {
          "type": "Buffer",
          "data": "hSC6aWsttPSfmz+CM0qweg4fj+RDQYktocSVyJYNbL/uoExT/g1l0eHFpp2bew29/ebo0/EwOmh3g7Gzn2YlbP4Tfz+AJIWSM42lAhdGyI61y9J0vTB2ase5pTLNonTzkwrI/At9zdSRL0UPKhaqELui2Mjuj+TZ8iqGKyqZJjU="
        },
        "indexValueMap": {
          "audY5mCwuzSlwtqmsaoG000r0npszF+RL71JFrmv/Ow=": {
            "valueMac": {
              "type": "Buffer",
              "data": "aH6UpVB0a9Q4LN8T8WOV+y0ckmBykVHSu3wrDyyXAyo="
            }
          }
        }
      },
      "regular_low": {
        "version": 1,
        "hash": {
          "type": "Buffer",
          "data": "DETEC9k6koGCT40bsLw+aooLbfnLAlTBHRh4ckKYK1ZT7CM0BeYZlDVDPJo53XQx15r6gYGlij4PJ8lUetMvin09LfYGOLLOplrWprlfry2OP0xPgcPiU04l1hSeVWXIfr0QtqKIROaBlsKm3FUZqaSse5tXdaxEDFStDUfRbQQ="
        },
        "indexValueMap": {
          "IVSSMNPG4zKzEbp6YrG+wBpsjdU4hVLsPhyYSZkSnD8=": {
            "valueMac": {
              "type": "Buffer",
              "data": "kB2XbfkgB6fkjiuk2ZgDaTCpyz2HXo7jnnKKfTQmqmg="
            }
          },
          "cO/mOvxUUZZzUbLogAbF2nmMhCVcmYcikymoWaA4+7w=": {
            "valueMac": {
              "type": "Buffer",
              "data": "r+7Fwze8hd89yLDuQEaYdo+4jbzoPHYxbx00gnPbpM8="
            }
          },
          "LVJzbAstbXnASZCGy3yLxmGaRnc/IjL2ddf0qnMEkkg=": {
            "valueMac": {
              "type": "Buffer",
              "data": "bAaVBrTqZVedXbCyrpJs2q0otyrH8oBmZQI+m4e1odE="
            }
          },
          "91M42FcJ/lYEta0fxD1jFGLMFcC5J1WDhAv6JCt/x4E=": {
            "valueMac": {
              "type": "Buffer",
              "data": "+3cAsqoMPTfViB9TgnDLQfN0/5k+W6gLw/5c79nbyEo="
            }
          },
          "KOmsAy9UWVAN+HQb9mbxLAfGvoJFgIkGdMKTCtbTZ7g=": {
            "valueMac": {
              "type": "Buffer",
              "data": "sq0I3sIfIbSk5e9/SEszvYvO83kUPdnZQ+Fiw5phgSU="
            }
          },
          "aGRLEwY3jOfeRvrYY/MhbnVf43hgDODbngUw/I8zaus=": {
            "valueMac": {
              "type": "Buffer",
              "data": "+cqqMZx2qNSJJpXUaOoJgqasof+xRlx9wjk+PKVAOsU="
            }
          },
          "I70CZqd/ckz/xTeY9PSHCCWRVlI4RisPt03zY5NasEo=": {
            "valueMac": {
              "type": "Buffer",
              "data": "pCxmFnjod/3M3uvF0NgNYV/P5ClW9GY7JJMcSWyEfaY="
            }
          }
        }
      }
    },
    "senderKeyMemory": {
      "120363045542910570@g.us": {
        "6281572757041@s.whatsapp.net": true,
        "6281236167286@s.whatsapp.net": true
      }
    }
  }
}